trytond/modules/import_product/README.rst
trytond/modules/import_product/__init__.py
trytond/modules/import_product/configuration.py
trytond/modules/import_product/configuration.xml
trytond/modules/import_product/message.xml
trytond/modules/import_product/product.py
trytond/modules/import_product/product.xml
trytond/modules/import_product/tryton.cfg
trytond/modules/import_product/versiondep.txt
trytond/modules/import_product/locale/de.po
trytond/modules/import_product/locale/en.po
trytond/modules/import_product/tests/__init__.py
trytond/modules/import_product/tests/test_product.py
trytond/modules/import_product/view/configuration_form.xml
trytond/modules/import_product/view/wiz_wizardcsvimport_schritt1_form.xml
trytond/modules/import_product/view/wiz_wizardcsvimport_schritt2_form.xml
mds_import_product-5.2.2.dist-info/METADATA
mds_import_product-5.2.2.dist-info/WHEEL
mds_import_product-5.2.2.dist-info/entry_points.txt
mds_import_product-5.2.2.dist-info/top_level.txt
mds_import_product-5.2.2.dist-info/RECORD
