Metadata-Version: 2.1
Name: mds-import-product
Version: 5.2.2
Summary: Tryton module to import csv-file to product
Home-page: https://www.m-ds.de/
Author: m-ds
Author-email: service@m-ds.de
License: GPL-3
Keywords: tryton product import csv
Platform: UNKNOWN
Classifier: Development Status :: 5 - Production/Stable
Classifier: Environment :: Plugins
Classifier: Framework :: Tryton
Classifier: Intended Audience :: Developers
Classifier: Intended Audience :: Customer Service
Classifier: Intended Audience :: Information Technology
Classifier: Topic :: Office/Business
Classifier: Natural Language :: German
Classifier: Natural Language :: English
Classifier: Operating System :: OS Independent
Classifier: License :: OSI Approved :: GNU General Public License (GPL)
Classifier: Programming Language :: Python :: 3.4
Classifier: Programming Language :: Python :: 3.5
Classifier: Programming Language :: Python :: 3.6
Requires-Dist: mds-csv-reader (>=1.0.4)
Requires-Dist: trytond-product (<5.3,>=5.2)
Requires-Dist: trytond-product-attribute (<5.3,>=5.2)
Requires-Dist: trytond-account-product (<5.3,>=5.2)
Requires-Dist: trytond (<5.3,>=5.2)
